pyIsoPEP/Dockerfile
pyIsoPEP/IsotonicPEP.py
pyIsoPEP/__init__.py
pyIsoPEP/main.py
pyIsoPEP/requirements.txt
pyisopep-0.1.3.dist-info/METADATA
pyisopep-0.1.3.dist-info/WHEEL
pyisopep-0.1.3.dist-info/entry_points.txt
pyisopep-0.1.3.dist-info/licenses/LICENSE
pyisopep-0.1.3.dist-info/RECORD
