Metadata-Version: 2.4
Name: pyIsoPEP
Version: 0.1.3
Summary: Estimate PEPs from empirical null models using isotonic regression.
Author-email: "Yuqi Zheng, Lukas Käll" <yuqi.zheng@scilifelab.se>
License:                                  Apache License
License-File: LICENSE
Requires-Python: >=3.9
Requires-Dist: numpy
Requires-Dist: pandas
Requires-Dist: scipy
Provides-Extra: dev
Requires-Dist: black; extra == 'dev'
Requires-Dist: pytest; extra == 'dev'
Requires-Dist: ruff; extra == 'dev'
